<document xmlns="http://maven.apache.org/changes/1.0.0"
          xmlns:xsi="http://www.w3.org/2001/XMLSchema-instance"
          xsi:schemaLocation="http://maven.apache.org/changes/1.0.0 http://maven.apache.org/xsd/changes-1.0.0.xsd">
	<body>
		<release version="3.4.1" date="2011-05-13">
			<action type="add" issue="195" dev="rombert">Html editor not shown for unsubmitted tasks</action>
			<action type="add" issue="196" dev="rombert">Collapse HTML editors unless interesting</action>
			<action type="add" issue="197" dev="rombert">Highlight HTML editors with incoming changes</action>
			<action type="add" issue="200" dev="rombert">Enabling the HTML editor should not clear the configuration</action>
			<action type="add" issue="006" dev="rombert">Open in browser do not work with queries</action>
		</release>
	</body>
</document>
